pygmalion/__init__.py
pygmalion/alias.py
pygmalion/cli.py
pygmalion/core.py
pygmalion/decorators.py
pygmalion/help.py
pygmalion/storage.py
pygmalion/tracker.py
pygmalion_cli_framework-0.1.2.dist-info/licenses/LICENSE
pygmalion_cli_framework-0.1.2.dist-info/METADATA
pygmalion_cli_framework-0.1.2.dist-info/WHEEL
pygmalion_cli_framework-0.1.2.dist-info/entry_points.txt
pygmalion_cli_framework-0.1.2.dist-info/top_level.txt
pygmalion_cli_framework-0.1.2.dist-info/RECORD
