Metadata-Version: 2.4
Name: pygmalion-cli-framework
Version: 0.1.2
Summary: A micro-framework for building adaptive CLI interfaces that learn from user behavior
Author: Pygmalion CLI Framework Developers
License: MIT
Project-URL: Homepage, https://github.com/Okymi-X/pygmalion-cli-framework
Project-URL: Repository, https://github.com/Okymi-X/pygmalion-cli-framework
Project-URL: Documentation, https://pygmalion-cli-framework.readthedocs.io
Keywords: cli,command-line,adaptive,learning,interface
Classifier: Development Status :: 4 - Beta
Classifier: Intended Audience :: Developers
Classifier: License :: OSI Approved :: MIT License
Classifier: Programming Language :: Python :: 3
Classifier: Programming Language :: Python :: 3.9
Classifier: Programming Language :: Python :: 3.10
Classifier: Programming Language :: Python :: 3.11
Classifier: Programming Language :: Python :: 3.12
Classifier: Programming Language :: Python :: 3.13
Classifier: Topic :: Software Development :: Libraries :: Python Modules
Classifier: Topic :: System :: System Shells
Classifier: Topic :: Terminals
Classifier: Topic :: Utilities
Classifier: Environment :: Console
Classifier: Operating System :: OS Independent
Requires-Python: >=3.9
License-File: LICENSE
Requires-Dist: click>=8.0.0
Requires-Dist: rich>=12.0.0
Provides-Extra: dev
Requires-Dist: pytest>=7.0.0; extra == "dev"
Requires-Dist: pytest-cov>=4.0.0; extra == "dev"
Requires-Dist: black>=22.0.0; extra == "dev"
Requires-Dist: flake8>=5.0.0; extra == "dev"
Requires-Dist: mypy>=1.0.0; extra == "dev"
Dynamic: license-file
